websocket_consumer/__init__.py
websocket_consumer/__main__.py
websocket_consumer-0.1.0.dist-info/METADATA
websocket_consumer-0.1.0.dist-info/WHEEL
websocket_consumer-0.1.0.dist-info/entry_points.txt
websocket_consumer-0.1.0.dist-info/top_level.txt
websocket_consumer-0.1.0.dist-info/RECORD
