Metadata-Version: 2.2
Name: websocket-consumer
Version: 0.1.0
Summary: Start an embedded websocket server from the root of your project.
Requires-Python: >=3.12
Requires-Dist: websockets>=15.0
